{
  "items": [
    {
      "sys": { "id": "1" },
      "fields": {
        "embeded": "<iframe src=\"https://www.facebook.com/plugins/post.php?href=https%3A%2F%2Fwww.facebook.com%2Frosaryplanthouse%2Fposts%2F108360117579021&show_text=true&width=500\" width=\"500\" height=\"393\" style=\"border:none;overflow:hidden\" scrolling=\"no\" frameborder=\"0\" allowfullscreen=\"true\" allow=\"autoplay; clipboard-write; encrypted-media; picture-in-picture; web-share\"></iframe>"
      }
    },
    {
      "sys": { "id": "2" },
      "fields": {
        "embeded": "<iframe src=\"https://www.facebook.com/plugins/post.php?href=https%3A%2F%2Fwww.facebook.com%2Frosaryplanthouse%2Fposts%2F110367237378309&show_text=true&width=500\" width=\"500\" height=\"609\" style=\"border:none;overflow:hidden\" scrolling=\"no\" frameborder=\"0\" allowfullscreen=\"true\" allow=\"autoplay; clipboard-write; encrypted-media; picture-in-picture; web-share\"></iframe>"
      }
    },
    {
      "sys": { "id": "3" },
      "fields": {
        "embeded": "<iframe src=\"https://www.facebook.com/plugins/post.php?href=https%3A%2F%2Fwww.facebook.com%2Frosaryplanthouse%2Fposts%2F112971113784588&show_text=true&width=500\" width=\"500\" height=\"589\" style=\"border:none;overflow:hidden\" scrolling=\"no\" frameborder=\"0\" allowfullscreen=\"true\" allow=\"autoplay; clipboard-write; encrypted-media; picture-in-picture; web-share\"></iframe>"
      }
    },
    {
      "sys": { "id": "4" },
      "fields": {
        "embeded": "<iframe src=\"https://www.facebook.com/plugins/post.php?href=https%3A%2F%2Fwww.facebook.com%2Frosaryplanthouse%2Fposts%2F119906553091044&show_text=true&width=500\" width=\"500\" height=\"578\" style=\"border:none;overflow:hidden\" scrolling=\"no\" frameborder=\"0\" allowfullscreen=\"true\" allow=\"autoplay; clipboard-write; encrypted-media; picture-in-picture; web-share\"></iframe>"
      }
    },
    {
      "sys": { "id": "5" },
      "fields": {
        "embeded": "<iframe src=\"https://www.facebook.com/plugins/post.php?href=https%3A%2F%2Fwww.facebook.com%2Frosaryplanthouse%2Fposts%2F124321852649514&show_text=true&width=500\" width=\"500\" height=\"609\" style=\"border:none;overflow:hidden\" scrolling=\"no\" frameborder=\"0\" allowfullscreen=\"true\" allow=\"autoplay; clipboard-write; encrypted-media; picture-in-picture; web-share\"></iframe>"
      }
    },
    {
      "sys": { "id": "6" },
      "fields": {
        "embeded": "<iframe src=\"https://www.facebook.com/plugins/post.php?href=https%3A%2F%2Fwww.facebook.com%2Frosaryplanthouse%2Fposts%2F128834728864893&show_text=true&width=500\" width=\"500\" height=\"435\" style=\"border:none;overflow:hidden\" scrolling=\"no\" frameborder=\"0\" allowfullscreen=\"true\" allow=\"autoplay; clipboard-write; encrypted-media; picture-in-picture; web-share\"></iframe>"
      }
    },
    {
      "sys": { "id": "7" },
      "fields": {
        "embeded": "<iframe src=\"https://www.facebook.com/plugins/post.php?href=https%3A%2F%2Fwww.facebook.com%2Frosaryplanthouse%2Fposts%2F128900542191645&show_text=true&width=500\" width=\"500\" height=\"246\" style=\"border:none;overflow:hidden\" scrolling=\"no\" frameborder=\"0\" allowfullscreen=\"true\" allow=\"autoplay; clipboard-write; encrypted-media; picture-in-picture; web-share\"></iframe>"
      }
    },
    {
      "sys": { "id": "8" },
      "fields": {
        "embeded": "<iframe src=\"https://www.facebook.com/plugins/post.php?href=https%3A%2F%2Fwww.facebook.com%2Frosaryplanthouse%2Fposts%2F142811234133909&show_text=true&width=500\" width=\"500\" height=\"628\" style=\"border:none;overflow:hidden\" scrolling=\"no\" frameborder=\"0\" allowfullscreen=\"true\" allow=\"autoplay; clipboard-write; encrypted-media; picture-in-picture; web-share\"></iframe>"
      }
    },
    {
      "sys": { "id": "9" },
      "fields": {
        "embeded": "<iframe src=\"https://www.facebook.com/plugins/post.php?href=https%3A%2F%2Fwww.facebook.com%2Frosaryplanthouse%2Fposts%2F142813040800395&show_text=true&width=500\" width=\"500\" height=\"361\" style=\"border:none;overflow:hidden\" scrolling=\"no\" frameborder=\"0\" allowfullscreen=\"true\" allow=\"autoplay; clipboard-write; encrypted-media; picture-in-picture; web-share\"></iframe>"
      }
    },
    {
      "sys": { "id": "10" },
      "fields": {
        "embeded": "<iframe src=\"https://www.facebook.com/plugins/post.php?href=https%3A%2F%2Fwww.facebook.com%2Frosaryplanthouse%2Fposts%2F142814814133551&show_text=true&width=500\" width=\"500\" height=\"645\" style=\"border:none;overflow:hidden\" scrolling=\"no\" frameborder=\"0\" allowfullscreen=\"true\" allow=\"autoplay; clipboard-write; encrypted-media; picture-in-picture; web-share\"></iframe>"
      }
    },
    {
      "sys": { "id": "11" },
      "fields": {
        "embeded": "<iframe src=\"https://www.facebook.com/plugins/post.php?href=https%3A%2F%2Fwww.facebook.com%2Frosaryplanthouse%2Fposts%2F142828834132149&show_text=true&width=500\" width=\"500\" height=\"800\" style=\"border:none;overflow:hidden\" scrolling=\"no\" frameborder=\"0\" allowfullscreen=\"true\" allow=\"autoplay; clipboard-write; encrypted-media; picture-in-picture; web-share\"></iframe>"
      }
    },
    {
      "sys": { "id": "12" },
      "fields": {
        "embeded": "<iframe src=\"https://www.facebook.com/plugins/post.php?href=https%3A%2F%2Fwww.facebook.com%2Frosaryplanthouse%2Fposts%2F143126730769026&show_text=true&width=500\" width=\"500\" height=\"474\" style=\"border:none;overflow:hidden\" scrolling=\"no\" frameborder=\"0\" allowfullscreen=\"true\" allow=\"autoplay; clipboard-write; encrypted-media; picture-in-picture; web-share\"></iframe>"
      }
    },
    {
      "sys": { "id": "13" },
      "fields": {
        "embeded": "<iframe src=\"https://www.facebook.com/plugins/post.php?href=https%3A%2F%2Fwww.facebook.com%2Frosaryplanthouse%2Fposts%2F143442300737469&show_text=true&width=500\" width=\"500\" height=\"590\" style=\"border:none;overflow:hidden\" scrolling=\"no\" frameborder=\"0\" allowfullscreen=\"true\" allow=\"autoplay; clipboard-write; encrypted-media; picture-in-picture; web-share\"></iframe>"
      }
    },
    {
      "sys": { "id": "14" },
      "fields": {
        "embeded": "<iframe src=\"https://www.facebook.com/plugins/post.php?href=https%3A%2F%2Fwww.facebook.com%2Frosaryplanthouse%2Fposts%2F144030604011972&show_text=true&width=500\" width=\"500\" height=\"608\" style=\"border:none;overflow:hidden\" scrolling=\"no\" frameborder=\"0\" allowfullscreen=\"true\" allow=\"autoplay; clipboard-write; encrypted-media; picture-in-picture; web-share\"></iframe>"
      }
    },
    {
      "sys": { "id": "15" },
      "fields": {
        "embeded": "<iframe src=\"https://www.facebook.com/plugins/post.php?href=https%3A%2F%2Fwww.facebook.com%2Frosaryplanthouse%2Fposts%2F146016927146673&show_text=true&width=500\" width=\"500\" height=\"575\" style=\"border:none;overflow:hidden\" scrolling=\"no\" frameborder=\"0\" allowfullscreen=\"true\" allow=\"autoplay; clipboard-write; encrypted-media; picture-in-picture; web-share\"></iframe>"
      }
    },
    {
      "sys": { "id": "16" },
      "fields": {
        "embeded": "<iframe src=\"https://www.facebook.com/plugins/post.php?href=https%3A%2F%2Fwww.facebook.com%2Frosaryplanthouse%2Fposts%2F148764336871932&show_text=true&width=500\" width=\"500\" height=\"610\" style=\"border:none;overflow:hidden\" scrolling=\"no\" frameborder=\"0\" allowfullscreen=\"true\" allow=\"autoplay; clipboard-write; encrypted-media; picture-in-picture; web-share\"></iframe>"
      }
    },
    {
      "sys": { "id": "17" },
      "fields": {
        "embeded": "<iframe src=\"https://www.facebook.com/plugins/post.php?href=https%3A%2F%2Fwww.facebook.com%2Frosaryplanthouse%2Fposts%2F150850849996614&show_text=true&width=500\" width=\"500\" height=\"448\" style=\"border:none;overflow:hidden\" scrolling=\"no\" frameborder=\"0\" allowfullscreen=\"true\" allow=\"autoplay; clipboard-write; encrypted-media; picture-in-picture; web-share\"></iframe>"
      }
    },
    {
      "sys": { "id": "18" },
      "fields": {
        "embeded": "<iframe src=\"https://www.facebook.com/plugins/post.php?href=https%3A%2F%2Fwww.facebook.com%2Frosaryplanthouse%2Fposts%2F151945689887130&show_text=true&width=500\" width=\"500\" height=\"590\" style=\"border:none;overflow:hidden\" scrolling=\"no\" frameborder=\"0\" allowfullscreen=\"true\" allow=\"autoplay; clipboard-write; encrypted-media; picture-in-picture; web-share\"></iframe>"
      }
    },
    {
      "sys": { "id": "19" },
      "fields": {
        "embeded": "<iframe src=\"https://www.facebook.com/plugins/post.php?href=https%3A%2F%2Fwww.facebook.com%2Frosaryplanthouse%2Fposts%2F152457723169260&show_text=true&width=500\" width=\"500\" height=\"498\" style=\"border:none;overflow:hidden\" scrolling=\"no\" frameborder=\"0\" allowfullscreen=\"true\" allow=\"autoplay; clipboard-write; encrypted-media; picture-in-picture; web-share\"></iframe>"
      }
    },
    {
      "sys": { "id": "20" },
      "fields": {
        "embeded": "<iframe src=\"https://www.facebook.com/plugins/post.php?href=https%3A%2F%2Fwww.facebook.com%2Frosaryplanthouse%2Fposts%2F152458816502484&show_text=true&width=500\" width=\"500\" height=\"610\" style=\"border:none;overflow:hidden\" scrolling=\"no\" frameborder=\"0\" allowfullscreen=\"true\" allow=\"autoplay; clipboard-write; encrypted-media; picture-in-picture; web-share\"></iframe>"
      }
    },
    {
      "sys": { "id": "21" },
      "fields": {
        "embeded": "<iframe src=\"https://www.facebook.com/plugins/post.php?href=https%3A%2F%2Fwww.facebook.com%2Frosaryplanthouse%2Fposts%2F152905856457780&show_text=true&width=500\" width=\"500\" height=\"214\" style=\"border:none;overflow:hidden\" scrolling=\"no\" frameborder=\"0\" allowfullscreen=\"true\" allow=\"autoplay; clipboard-write; encrypted-media; picture-in-picture; web-share\"></iframe>"
      }
    },
    {
      "sys": { "id": "22" },
      "fields": {
        "embeded": "<iframe src=\"https://www.facebook.com/plugins/post.php?href=https%3A%2F%2Fwww.facebook.com%2Frosaryplanthouse%2Fposts%2F153149263100106&show_text=true&width=500\" width=\"500\" height=\"486\" style=\"border:none;overflow:hidden\" scrolling=\"no\" frameborder=\"0\" allowfullscreen=\"true\" allow=\"autoplay; clipboard-write; encrypted-media; picture-in-picture; web-share\"></iframe>"
      }
    },
    {
      "sys": { "id": "23" },
      "fields": {
        "embeded": "<iframe src=\"https://www.facebook.com/plugins/post.php?href=https%3A%2F%2Fwww.facebook.com%2Frosaryplanthouse%2Fposts%2F153423989739300&show_text=true&width=500\" width=\"500\" height=\"629\" style=\"border:none;overflow:hidden\" scrolling=\"no\" frameborder=\"0\" allowfullscreen=\"true\" allow=\"autoplay; clipboard-write; encrypted-media; picture-in-picture; web-share\"></iframe>"
      }
    },
    {
      "sys": { "id": "24" },
      "fields": {
        "embeded": "<iframe src=\"https://www.facebook.com/plugins/post.php?href=https%3A%2F%2Fwww.facebook.com%2Frosaryplanthouse%2Fposts%2F153836223031410&show_text=true&width=500\" width=\"500\" height=\"549\" style=\"border:none;overflow:hidden\" scrolling=\"no\" frameborder=\"0\" allowfullscreen=\"true\" allow=\"autoplay; clipboard-write; encrypted-media; picture-in-picture; web-share\"></iframe>"
      }
    },
    {
      "sys": { "id": "25" },
      "fields": {
        "embeded": "<iframe src=\"https://www.facebook.com/plugins/post.php?href=https%3A%2F%2Fwww.facebook.com%2Frosaryplanthouse%2Fposts%2F156542952760737&show_text=true&width=500\" width=\"500\" height=\"589\" style=\"border:none;overflow:hidden\" scrolling=\"no\" frameborder=\"0\" allowfullscreen=\"true\" allow=\"autoplay; clipboard-write; encrypted-media; picture-in-picture; web-share\"></iframe>"
      }
    },
    {
      "sys": { "id": "26" },
      "fields": {
        "embeded": "<iframe src=\"https://www.facebook.com/plugins/post.php?href=https%3A%2F%2Fwww.facebook.com%2Frosaryplanthouse%2Fposts%2F156811629400536&show_text=true&width=500\" width=\"500\" height=\"665\" style=\"border:none;overflow:hidden\" scrolling=\"no\" frameborder=\"0\" allowfullscreen=\"true\" allow=\"autoplay; clipboard-write; encrypted-media; picture-in-picture; web-share\"></iframe>"
      }
    },
    {
      "sys": { "id": "27" },
      "fields": {
        "embeded": "<iframe src=\"https://www.facebook.com/plugins/post.php?href=https%3A%2F%2Fwww.facebook.com%2Frosaryplanthouse%2Fposts%2F163860305362335&show_text=true&width=500\" width=\"500\" height=\"416\" style=\"border:none;overflow:hidden\" scrolling=\"no\" frameborder=\"0\" allowfullscreen=\"true\" allow=\"autoplay; clipboard-write; encrypted-media; picture-in-picture; web-share\"></iframe>"
      }
    },
    {
      "sys": { "id": "28" },
      "fields": {
        "embeded": "<iframe src=\"https://www.facebook.com/plugins/post.php?href=https%3A%2F%2Fwww.facebook.com%2Frosaryplanthouse%2Fposts%2F164084498673249&show_text=true&width=500\" width=\"500\" height=\"582\" style=\"border:none;overflow:hidden\" scrolling=\"no\" frameborder=\"0\" allowfullscreen=\"true\" allow=\"autoplay; clipboard-write; encrypted-media; picture-in-picture; web-share\"></iframe>"
      }
    },
    {
      "sys": { "id": "29" },
      "fields": {
        "embeded": "<iframe src=\"https://www.facebook.com/plugins/post.php?href=https%3A%2F%2Fwww.facebook.com%2Frosaryplanthouse%2Fposts%2F164145828667116&show_text=true&width=500\" width=\"500\" height=\"665\" style=\"border:none;overflow:hidden\" scrolling=\"no\" frameborder=\"0\" allowfullscreen=\"true\" allow=\"autoplay; clipboard-write; encrypted-media; picture-in-picture; web-share\"></iframe>"
      }
    },
    {
      "sys": { "id": "30" },
      "fields": {
        "embeded": "<iframe src=\"https://www.facebook.com/plugins/post.php?href=https%3A%2F%2Fwww.facebook.com%2Frosaryplanthouse%2Fposts%2F164242018657497&show_text=true&width=500\" width=\"500\" height=\"665\" style=\"border:none;overflow:hidden\" scrolling=\"no\" frameborder=\"0\" allowfullscreen=\"true\" allow=\"autoplay; clipboard-write; encrypted-media; picture-in-picture; web-share\"></iframe>"
      }
    },
    {
      "sys": { "id": "31" },
      "fields": {
        "embeded": "<iframe src=\"https://www.facebook.com/plugins/post.php?href=https%3A%2F%2Fwww.facebook.com%2Frosaryplanthouse%2Fposts%2F164244571990575&show_text=true&width=500\" width=\"500\" height=\"647\" style=\"border:none;overflow:hidden\" scrolling=\"no\" frameborder=\"0\" allowfullscreen=\"true\" allow=\"autoplay; clipboard-write; encrypted-media; picture-in-picture; web-share\"></iframe>"
      }
    },
    {
      "sys": { "id": "32" },
      "fields": {
        "embeded": "<iframe src=\"https://www.facebook.com/plugins/post.php?href=https%3A%2F%2Fwww.facebook.com%2Frosaryplanthouse%2Fposts%2F164249321990100&show_text=true&width=500\" width=\"500\" height=\"703\" style=\"border:none;overflow:hidden\" scrolling=\"no\" frameborder=\"0\" allowfullscreen=\"true\" allow=\"autoplay; clipboard-write; encrypted-media; picture-in-picture; web-share\"></iframe>"
      }
    },
    {
      "sys": { "id": "33" },
      "fields": {
        "embeded": "<iframe src=\"https://www.facebook.com/plugins/post.php?href=https%3A%2F%2Fwww.facebook.com%2Frosaryplanthouse%2Fposts%2F164520031963029&show_text=true&width=500\" width=\"500\" height=\"665\" style=\"border:none;overflow:hidden\" scrolling=\"no\" frameborder=\"0\" allowfullscreen=\"true\" allow=\"autoplay; clipboard-write; encrypted-media; picture-in-picture; web-share\"></iframe>"
      }
    },
    {
      "sys": { "id": "34" },
      "fields": {
        "embeded": "<iframe src=\"https://www.facebook.com/plugins/post.php?href=https%3A%2F%2Fwww.facebook.com%2Frosaryplanthouse%2Fposts%2F164718005276565&show_text=true&width=500\" width=\"500\" height=\"487\" style=\"border:none;overflow:hidden\" scrolling=\"no\" frameborder=\"0\" allowfullscreen=\"true\" allow=\"autoplay; clipboard-write; encrypted-media; picture-in-picture; web-share\"></iframe>"
      }
    },
    {
      "sys": { "id": "35" },
      "fields": {
        "embeded": "<iframe src=\"https://www.facebook.com/plugins/post.php?href=https%3A%2F%2Fwww.facebook.com%2Frosaryplanthouse%2Fposts%2F164864035261962&show_text=true&width=500\" width=\"500\" height=\"487\" style=\"border:none;overflow:hidden\" scrolling=\"no\" frameborder=\"0\" allowfullscreen=\"true\" allow=\"autoplay; clipboard-write; encrypted-media; picture-in-picture; web-share\"></iframe>"
      }
    },
    {
      "sys": { "id": "36" },
      "fields": {
        "embeded": "<iframe src=\"https://www.facebook.com/plugins/post.php?href=https%3A%2F%2Fwww.facebook.com%2Frosaryplanthouse%2Fposts%2F165348438546855&show_text=true&width=500\" width=\"500\" height=\"628\" style=\"border:none;overflow:hidden\" scrolling=\"no\" frameborder=\"0\" allowfullscreen=\"true\" allow=\"autoplay; clipboard-write; encrypted-media; picture-in-picture; web-share\"></iframe>"
      }
    },
    {
      "sys": { "id": "37" },
      "fields": {
        "embeded": "<iframe src=\"https://www.facebook.com/plugins/post.php?href=https%3A%2F%2Fwww.facebook.com%2Frosaryplanthouse%2Fposts%2F168229894925376&show_text=true&width=500\" width=\"500\" height=\"486\" style=\"border:none;overflow:hidden\" scrolling=\"no\" frameborder=\"0\" allowfullscreen=\"true\" allow=\"autoplay; clipboard-write; encrypted-media; picture-in-picture; web-share\"></iframe>"
      }
    },
    {
      "sys": { "id": "38" },
      "fields": {
        "embeded": "<iframe src=\"https://www.facebook.com/plugins/post.php?href=https%3A%2F%2Fwww.facebook.com%2Frosaryplanthouse%2Fposts%2F170563644692001&show_text=true&width=500\" width=\"500\" height=\"601\" style=\"border:none;overflow:hidden\" scrolling=\"no\" frameborder=\"0\" allowfullscreen=\"true\" allow=\"autoplay; clipboard-write; encrypted-media; picture-in-picture; web-share\"></iframe>"
      }
    },
    {
      "sys": { "id": "39" },
      "fields": {
        "embeded": "<iframe src=\"https://www.facebook.com/plugins/post.php?href=https%3A%2F%2Fwww.facebook.com%2Frosaryplanthouse%2Fposts%2F173142144434151&show_text=true&width=500\" width=\"500\" height=\"169\" style=\"border:none;overflow:hidden\" scrolling=\"no\" frameborder=\"0\" allowfullscreen=\"true\" allow=\"autoplay; clipboard-write; encrypted-media; picture-in-picture; web-share\"></iframe>"
      }
    },
    {
      "sys": { "id": "40" },
      "fields": {
        "embeded": "<iframe src=\"https://www.facebook.com/plugins/post.php?href=https%3A%2F%2Fwww.facebook.com%2Frosaryplanthouse%2Fposts%2F174057127675986&show_text=true&width=500\" width=\"500\" height=\"227\" style=\"border:none;overflow:hidden\" scrolling=\"no\" frameborder=\"0\" allowfullscreen=\"true\" allow=\"autoplay; clipboard-write; encrypted-media; picture-in-picture; web-share\"></iframe>"
      }
    },
    {
      "sys": { "id": "41" },
      "fields": {
        "embeded": "<iframe src=\"https://www.facebook.com/plugins/post.php?href=https%3A%2F%2Fwww.facebook.com%2Frosaryplanthouse%2Fposts%2F175079267573772&show_text=true&width=500\" width=\"500\" height=\"188\" style=\"border:none;overflow:hidden\" scrolling=\"no\" frameborder=\"0\" allowfullscreen=\"true\" allow=\"autoplay; clipboard-write; encrypted-media; picture-in-picture; web-share\"></iframe>"
      }
    },
    {
      "sys": { "id": "42" },
      "fields": {
        "embeded": "<iframe src=\"https://www.facebook.com/plugins/post.php?href=https%3A%2F%2Fwww.facebook.com%2Frosaryplanthouse%2Fposts%2F177145470700485&show_text=true&width=500\" width=\"500\" height=\"601\" style=\"border:none;overflow:hidden\" scrolling=\"no\" frameborder=\"0\" allowfullscreen=\"true\" allow=\"autoplay; clipboard-write; encrypted-media; picture-in-picture; web-share\"></iframe>"
      }
    },
    {
      "sys": { "id": "43" },
      "fields": {
        "embeded": "<iframe src=\"https://www.facebook.com/plugins/post.php?href=https%3A%2F%2Fwww.facebook.com%2Frosaryplanthouse%2Fposts%2F180415450373487&show_text=true&width=500\" width=\"500\" height=\"610\" style=\"border:none;overflow:hidden\" scrolling=\"no\" frameborder=\"0\" allowfullscreen=\"true\" allow=\"autoplay; clipboard-write; encrypted-media; picture-in-picture; web-share\"></iframe>"
      }
    },
    {
      "sys": { "id": "44" },
      "fields": {
        "embeded": "<iframe src=\"https://www.facebook.com/plugins/post.php?href=https%3A%2F%2Fwww.facebook.com%2Frosaryplanthouse%2Fposts%2F188091886272510&show_text=true&width=500\" width=\"500\" height=\"594\" style=\"border:none;overflow:hidden\" scrolling=\"no\" frameborder=\"0\" allowfullscreen=\"true\" allow=\"autoplay; clipboard-write; encrypted-media; picture-in-picture; web-share\"></iframe>"
      }
    },
    {
      "sys": { "id": "45" },
      "fields": {
        "embeded": "<iframe src=\"https://www.facebook.com/plugins/post.php?href=https%3A%2F%2Fwww.facebook.com%2Frosaryplanthouse%2Fposts%2F188124349602597&show_text=true&width=500\" width=\"500\" height=\"610\" style=\"border:none;overflow:hidden\" scrolling=\"no\" frameborder=\"0\" allowfullscreen=\"true\" allow=\"autoplay; clipboard-write; encrypted-media; picture-in-picture; web-share\"></iframe>"
      }
    },
    {
      "sys": { "id": "46" },
      "fields": {
        "embeded": "<iframe src=\"https://www.facebook.com/plugins/post.php?href=https%3A%2F%2Fwww.facebook.com%2Frosaryplanthouse%2Fposts%2F188293802918985&show_text=true&width=500\" width=\"500\" height=\"609\" style=\"border:none;overflow:hidden\" scrolling=\"no\" frameborder=\"0\" allowfullscreen=\"true\" allow=\"autoplay; clipboard-write; encrypted-media; picture-in-picture; web-share\"></iframe>"
      }
    },
    {
      "sys": { "id": "47" },
      "fields": {
        "embeded": "<iframe src=\"https://www.facebook.com/plugins/post.php?href=https%3A%2F%2Fwww.facebook.com%2Frosaryplanthouse%2Fposts%2F194587635622935&show_text=true&width=500\" width=\"500\" height=\"645\" style=\"border:none;overflow:hidden\" scrolling=\"no\" frameborder=\"0\" allowfullscreen=\"true\" allow=\"autoplay; clipboard-write; encrypted-media; picture-in-picture; web-share\"></iframe>"
      }
    },
    {
      "sys": { "id": "48" },
      "fields": {
        "embeded": "<iframe src=\"https://www.facebook.com/plugins/post.php?href=https%3A%2F%2Fwww.facebook.com%2Frosaryplanthouse%2Fposts%2F196139075467791&show_text=true&width=500\" width=\"500\" height=\"610\" style=\"border:none;overflow:hidden\" scrolling=\"no\" frameborder=\"0\" allowfullscreen=\"true\" allow=\"autoplay; clipboard-write; encrypted-media; picture-in-picture; web-share\"></iframe>"
      }
    },
    {
      "sys": { "id": "49" },
      "fields": {
        "embeded": "<iframe src=\"https://www.facebook.com/plugins/post.php?href=https%3A%2F%2Fwww.facebook.com%2Frosaryplanthouse%2Fposts%2F197063015375397&show_text=true&width=500\" width=\"500\" height=\"601\" style=\"border:none;overflow:hidden\" scrolling=\"no\" frameborder=\"0\" allowfullscreen=\"true\" allow=\"autoplay; clipboard-write; encrypted-media; picture-in-picture; web-share\"></iframe>"
      }
    },
    {
      "sys": { "id": "50" },
      "fields": {
        "embeded": "<iframe src=\"https://www.facebook.com/plugins/post.php?href=https%3A%2F%2Fwww.facebook.com%2Frosaryplanthouse%2Fposts%2F197545465327152&show_text=true&width=500\" width=\"500\" height=\"590\" style=\"border:none;overflow:hidden\" scrolling=\"no\" frameborder=\"0\" allowfullscreen=\"true\" allow=\"autoplay; clipboard-write; encrypted-media; picture-in-picture; web-share\"></iframe>"
      }
    },
    {
      "sys": { "id": "51" },
      "fields": {
        "embeded": "<iframe src=\"https://www.facebook.com/plugins/post.php?href=https%3A%2F%2Fwww.facebook.com%2Frosaryplanthouse%2Fposts%2F200724431675922&show_text=true&width=500\" width=\"500\" height=\"505\" style=\"border:none;overflow:hidden\" scrolling=\"no\" frameborder=\"0\" allowfullscreen=\"true\" allow=\"autoplay; clipboard-write; encrypted-media; picture-in-picture; web-share\"></iframe>"
      }
    },
    {
      "sys": { "id": "52" },
      "fields": {
        "embeded": "<iframe src=\"https://www.facebook.com/plugins/post.php?href=https%3A%2F%2Fwww.facebook.com%2Frosaryplanthouse%2Fposts%2F201517851596580&show_text=true&width=500\" width=\"500\" height=\"188\" style=\"border:none;overflow:hidden\" scrolling=\"no\" frameborder=\"0\" allowfullscreen=\"true\" allow=\"autoplay; clipboard-write; encrypted-media; picture-in-picture; web-share\"></iframe>"
      }
    },
    {
      "sys": { "id": "53" },
      "fields": {
        "embeded": "<iframe src=\"https://www.facebook.com/plugins/post.php?href=https%3A%2F%2Fwww.facebook.com%2Frosaryplanthouse%2Fposts%2F201737704907928&show_text=true&width=500\" width=\"500\" height=\"665\" style=\"border:none;overflow:hidden\" scrolling=\"no\" frameborder=\"0\" allowfullscreen=\"true\" allow=\"autoplay; clipboard-write; encrypted-media; picture-in-picture; web-share\"></iframe>"
      }
    },
    {
      "sys": { "id": "54" },
      "fields": {
        "embeded": "<iframe src=\"https://www.facebook.com/plugins/post.php?href=https%3A%2F%2Fwww.facebook.com%2Frosaryplanthouse%2Fposts%2F207950684286630&show_text=true&width=500\" width=\"500\" height=\"486\" style=\"border:none;overflow:hidden\" scrolling=\"no\" frameborder=\"0\" allowfullscreen=\"true\" allow=\"autoplay; clipboard-write; encrypted-media; picture-in-picture; web-share\"></iframe>"
      }
    },
    {
      "sys": { "id": "55" },
      "fields": {
        "embeded": "<iframe src=\"https://www.facebook.com/plugins/post.php?href=https%3A%2F%2Fwww.facebook.com%2Frosaryplanthouse%2Fposts%2F207968517618180&show_text=true&width=500\" width=\"500\" height=\"503\" style=\"border:none;overflow:hidden\" scrolling=\"no\" frameborder=\"0\" allowfullscreen=\"true\" allow=\"autoplay; clipboard-write; encrypted-media; picture-in-picture; web-share\"></iframe>"
      }
    },
    {
      "sys": { "id": "56" },
      "fields": {
        "embeded": "<iframe src=\"https://www.facebook.com/plugins/post.php?href=https%3A%2F%2Fwww.facebook.com%2Frosaryplanthouse%2Fposts%2F228521875562844&show_text=true&width=500\" width=\"500\" height=\"350\" style=\"border:none;overflow:hidden\" scrolling=\"no\" frameborder=\"0\" allowfullscreen=\"true\" allow=\"autoplay; clipboard-write; encrypted-media; picture-in-picture; web-share\"></iframe>"
      }
    },
    {
      "sys": { "id": "57" },
      "fields": {
        "embeded": "<iframe src=\"https://www.facebook.com/plugins/post.php?href=https%3A%2F%2Fwww.facebook.com%2Frosaryplanthouse%2Fposts%2F228764952205203&show_text=true&width=500\" width=\"500\" height=\"645\" style=\"border:none;overflow:hidden\" scrolling=\"no\" frameborder=\"0\" allowfullscreen=\"true\" allow=\"autoplay; clipboard-write; encrypted-media; picture-in-picture; web-share\"></iframe>"
      }
    },
    {
      "sys": { "id": "58" },
      "fields": {
        "embeded": "<iframe src=\"https://www.facebook.com/plugins/post.php?href=https%3A%2F%2Fwww.facebook.com%2Frosaryplanthouse%2Fposts%2F233515978396767&show_text=true&width=500\" width=\"500\" height=\"464\" style=\"border:none;overflow:hidden\" scrolling=\"no\" frameborder=\"0\" allowfullscreen=\"true\" allow=\"autoplay; clipboard-write; encrypted-media; picture-in-picture; web-share\"></iframe>"
      }
    },
    {
      "sys": { "id": "59" },
      "fields": {
        "embeded": "<iframe src=\"https://www.facebook.com/plugins/post.php?href=https%3A%2F%2Fwww.facebook.com%2Frosaryplanthouse%2Fposts%2F233880601693638&show_text=true&width=500\" width=\"500\" height=\"665\" style=\"border:none;overflow:hidden\" scrolling=\"no\" frameborder=\"0\" allowfullscreen=\"true\" allow=\"autoplay; clipboard-write; encrypted-media; picture-in-picture; web-share\"></iframe>"
      }
    },
    {
      "sys": { "id": "60" },
      "fields": {
        "embeded": "<iframe src=\"https://www.facebook.com/plugins/post.php?href=https%3A%2F%2Fwww.facebook.com%2Frosaryplanthouse%2Fposts%2F233926861689012&show_text=true&width=500\" width=\"500\" height=\"629\" style=\"border:none;overflow:hidden\" scrolling=\"no\" frameborder=\"0\" allowfullscreen=\"true\" allow=\"autoplay; clipboard-write; encrypted-media; picture-in-picture; web-share\"></iframe>"
      }
    },
    {
      "sys": { "id": "61" },
      "fields": {
        "embeded": "<iframe src=\"https://www.facebook.com/plugins/post.php?href=https%3A%2F%2Fwww.facebook.com%2Frosaryplanthouse%2Fposts%2F234985961583102&show_text=true&width=500\" width=\"500\" height=\"609\" style=\"border:none;overflow:hidden\" scrolling=\"no\" frameborder=\"0\" allowfullscreen=\"true\" allow=\"autoplay; clipboard-write; encrypted-media; picture-in-picture; web-share\"></iframe>"
      }
    },
    {
      "sys": { "id": "62" },
      "fields": {
        "embeded": "<iframe src=\"https://www.facebook.com/plugins/post.php?href=https%3A%2F%2Fwww.facebook.com%2Frosaryplanthouse%2Fposts%2F238265861255112&show_text=true&width=500\" width=\"500\" height=\"609\" style=\"border:none;overflow:hidden\" scrolling=\"no\" frameborder=\"0\" allowfullscreen=\"true\" allow=\"autoplay; clipboard-write; encrypted-media; picture-in-picture; web-share\"></iframe>"
      }
    },
    {
      "sys": { "id": "63" },
      "fields": {
        "embeded": "<iframe src=\"https://www.facebook.com/plugins/post.php?href=https%3A%2F%2Fwww.facebook.com%2Frosaryplanthouse%2Fposts%2F243714514043580&show_text=true&width=500\" width=\"500\" height=\"609\" style=\"border:none;overflow:hidden\" scrolling=\"no\" frameborder=\"0\" allowfullscreen=\"true\" allow=\"autoplay; clipboard-write; encrypted-media; picture-in-picture; web-share\"></iframe>"
      }
    },
    {
      "sys": { "id": "64" },
      "fields": {
        "embeded": "<iframe src=\"https://www.facebook.com/plugins/post.php?href=https%3A%2F%2Fwww.facebook.com%2Frosaryplanthouse%2Fposts%2F246834413731590&show_text=true&width=500\" width=\"500\" height=\"177\" style=\"border:none;overflow:hidden\" scrolling=\"no\" frameborder=\"0\" allowfullscreen=\"true\" allow=\"autoplay; clipboard-write; encrypted-media; picture-in-picture; web-share\"></iframe>"
      }
    },
    {
      "sys": { "id": "65" },
      "fields": {
        "embeded": "<iframe src=\"https://www.facebook.com/plugins/post.php?href=https%3A%2F%2Fwww.facebook.com%2Frosaryplanthouse%2Fposts%2F247449310336767&show_text=true&width=500\" width=\"500\" height=\"416\" style=\"border:none;overflow:hidden\" scrolling=\"no\" frameborder=\"0\" allowfullscreen=\"true\" allow=\"autoplay; clipboard-write; encrypted-media; picture-in-picture; web-share\"></iframe>"
      }
    },
    {
      "sys": { "id": "66" },
      "fields": {
        "embeded": "<iframe src=\"https://www.facebook.com/plugins/post.php?href=https%3A%2F%2Fwww.facebook.com%2Frosaryplanthouse%2Fposts%2F247463960335302&show_text=true&width=500\" width=\"500\" height=\"628\" style=\"border:none;overflow:hidden\" scrolling=\"no\" frameborder=\"0\" allowfullscreen=\"true\" allow=\"autoplay; clipboard-write; encrypted-media; picture-in-picture; web-share\"></iframe>"
      }
    },
    {
      "sys": { "id": "67" },
      "fields": {
        "embeded": "<iframe src=\"https://www.facebook.com/plugins/post.php?href=https%3A%2F%2Fwww.facebook.com%2Frosaryplanthouse%2Fposts%2F250748386673526&show_text=true&width=500\" width=\"500\" height=\"486\" style=\"border:none;overflow:hidden\" scrolling=\"no\" frameborder=\"0\" allowfullscreen=\"true\" allow=\"autoplay; clipboard-write; encrypted-media; picture-in-picture; web-share\"></iframe>"
      }
    },
    {
      "sys": { "id": "68" },
      "fields": {
        "embeded": "<iframe src=\"https://www.facebook.com/plugins/post.php?href=https%3A%2F%2Fwww.facebook.com%2Frosaryplanthouse%2Fposts%2F251626639919034&show_text=true&width=500\" width=\"500\" height=\"186\" style=\"border:none;overflow:hidden\" scrolling=\"no\" frameborder=\"0\" allowfullscreen=\"true\" allow=\"autoplay; clipboard-write; encrypted-media; picture-in-picture; web-share\"></iframe>"
      }
    },
    {
      "sys": { "id": "69" },
      "fields": {
        "embeded": "<iframe src=\"https://www.facebook.com/plugins/post.php?href=https%3A%2F%2Fwww.facebook.com%2Frosaryplanthouse%2Fposts%2F251766549905043&show_text=true&width=500\" width=\"500\" height=\"665\" style=\"border:none;overflow:hidden\" scrolling=\"no\" frameborder=\"0\" allowfullscreen=\"true\" allow=\"autoplay; clipboard-write; encrypted-media; picture-in-picture; web-share\"></iframe>"
      }
    },
    {
      "sys": { "id": "70" },
      "fields": {
        "embeded": "<iframe src=\"https://www.facebook.com/plugins/post.php?href=https%3A%2F%2Fwww.facebook.com%2Frosaryplanthouse%2Fposts%2F256111069470591&show_text=true&width=500\" width=\"500\" height=\"609\" style=\"border:none;overflow:hidden\" scrolling=\"no\" frameborder=\"0\" allowfullscreen=\"true\" allow=\"autoplay; clipboard-write; encrypted-media; picture-in-picture; web-share\"></iframe>"
      }
    },
    {
      "sys": { "id": "71" },
      "fields": {
        "embeded": "<iframe src=\"https://www.facebook.com/plugins/post.php?href=https%3A%2F%2Fwww.facebook.com%2Frosaryplanthouse%2Fposts%2F256872366061128&show_text=true&width=500\" width=\"500\" height=\"582\" style=\"border:none;overflow:hidden\" scrolling=\"no\" frameborder=\"0\" allowfullscreen=\"true\" allow=\"autoplay; clipboard-write; encrypted-media; picture-in-picture; web-share\"></iframe>"
      }
    },
    {
      "sys": { "id": "72" },
      "fields": {
        "embeded": "<iframe src=\"https://www.facebook.com/plugins/post.php?href=https%3A%2F%2Fwww.facebook.com%2Frosaryplanthouse%2Fposts%2F259617672453264&show_text=true&width=500\" width=\"500\" height=\"665\" style=\"border:none;overflow:hidden\" scrolling=\"no\" frameborder=\"0\" allowfullscreen=\"true\" allow=\"autoplay; clipboard-write; encrypted-media; picture-in-picture; web-share\"></iframe>"
      }
    },
    {
      "sys": { "id": "73" },
      "fields": {
        "embeded": "<iframe src=\"https://www.facebook.com/plugins/post.php?href=https%3A%2F%2Fwww.facebook.com%2Frosaryplanthouse%2Fposts%2F259623855785979&show_text=true&width=500\" width=\"500\" height=\"620\" style=\"border:none;overflow:hidden\" scrolling=\"no\" frameborder=\"0\" allowfullscreen=\"true\" allow=\"autoplay; clipboard-write; encrypted-media; picture-in-picture; web-share\"></iframe>"
      }
    },
    {
      "sys": { "id": "74" },
      "fields": {
        "embeded": "<iframe src=\"https://www.facebook.com/plugins/post.php?href=https%3A%2F%2Fwww.facebook.com%2Frosaryplanthouse%2Fposts%2F263909762024055&show_text=true&width=500\" width=\"500\" height=\"169\" style=\"border:none;overflow:hidden\" scrolling=\"no\" frameborder=\"0\" allowfullscreen=\"true\" allow=\"autoplay; clipboard-write; encrypted-media; picture-in-picture; web-share\"></iframe>"
      }
    },
    {
      "sys": { "id": "75" },
      "fields": {
        "embeded": "<iframe src=\"https://www.facebook.com/plugins/post.php?href=https%3A%2F%2Fwww.facebook.com%2Frosaryplanthouse%2Fposts%2F267164951698536&show_text=true&width=500\" width=\"500\" height=\"411\" style=\"border:none;overflow:hidden\" scrolling=\"no\" frameborder=\"0\" allowfullscreen=\"true\" allow=\"autoplay; clipboard-write; encrypted-media; picture-in-picture; web-share\"></iframe>"
      }
    },
    {
      "sys": { "id": "76" },
      "fields": {
        "embeded": "<iframe src=\"https://www.facebook.com/plugins/post.php?href=https%3A%2F%2Fwww.facebook.com%2Frosaryplanthouse%2Fposts%2F270495884698776&show_text=true&width=500\" width=\"500\" height=\"556\" style=\"border:none;overflow:hidden\" scrolling=\"no\" frameborder=\"0\" allowfullscreen=\"true\" allow=\"autoplay; clipboard-write; encrypted-media; picture-in-picture; web-share\"></iframe>"
      }
    },
    {
      "sys": { "id": "77" },
      "fields": {
        "embeded": "<iframe src=\"https://www.facebook.com/plugins/post.php?href=https%3A%2F%2Fwww.facebook.com%2Frosaryplanthouse%2Fposts%2F287489192999445&show_text=true&width=500\" width=\"500\" height=\"610\" style=\"border:none;overflow:hidden\" scrolling=\"no\" frameborder=\"0\" allowfullscreen=\"true\" allow=\"autoplay; clipboard-write; encrypted-media; picture-in-picture; web-share\"></iframe>"
      }
    },
    {
      "sys": { "id": "78" },
      "fields": {
        "embeded": "<iframe src=\"https://www.facebook.com/plugins/post.php?href=https%3A%2F%2Fwww.facebook.com%2Frosaryplanthouse%2Fposts%2F287652022983162&show_text=true&width=500\" width=\"500\" height=\"207\" style=\"border:none;overflow:hidden\" scrolling=\"no\" frameborder=\"0\" allowfullscreen=\"true\" allow=\"autoplay; clipboard-write; encrypted-media; picture-in-picture; web-share\"></iframe>"
      }
    },
    {
      "sys": { "id": "79" },
      "fields": {
        "embeded": "<iframe src=\"https://www.facebook.com/plugins/post.php?href=https%3A%2F%2Fwww.facebook.com%2Frosaryplanthouse%2Fposts%2F288171166264581&show_text=true&width=500\" width=\"500\" height=\"678\" style=\"border:none;overflow:hidden\" scrolling=\"no\" frameborder=\"0\" allowfullscreen=\"true\" allow=\"autoplay; clipboard-write; encrypted-media; picture-in-picture; web-share\"></iframe>"
      }
    },
    {
      "sys": { "id": "80" },
      "fields": {
        "embeded": "<iframe src=\"https://www.facebook.com/plugins/post.php?href=https%3A%2F%2Fwww.facebook.com%2Frosaryplanthouse%2Fposts%2F290918329323198&show_text=true&width=500\" width=\"500\" height=\"647\" style=\"border:none;overflow:hidden\" scrolling=\"no\" frameborder=\"0\" allowfullscreen=\"true\" allow=\"autoplay; clipboard-write; encrypted-media; picture-in-picture; web-share\"></iframe>"
      }
    },
    {
      "sys": { "id": "81" },
      "fields": {
        "embeded": "<iframe src=\"https://www.facebook.com/plugins/post.php?href=https%3A%2F%2Fwww.facebook.com%2Frosaryplanthouse%2Fposts%2F297015798713451&show_text=true&width=500\" width=\"500\" height=\"188\" style=\"border:none;overflow:hidden\" scrolling=\"no\" frameborder=\"0\" allowfullscreen=\"true\" allow=\"autoplay; clipboard-write; encrypted-media; picture-in-picture; web-share\"></iframe>"
      }
    },
    {
      "sys": { "id": "82" },
      "fields": {
        "embeded": "<iframe src=\"https://www.facebook.com/plugins/post.php?href=https%3A%2F%2Fwww.facebook.com%2Frosaryplanthouse%2Fposts%2F297221405359557&show_text=true&width=500\" width=\"500\" height=\"227\" style=\"border:none;overflow:hidden\" scrolling=\"no\" frameborder=\"0\" allowfullscreen=\"true\" allow=\"autoplay; clipboard-write; encrypted-media; picture-in-picture; web-share\"></iframe>"
      }
    },
    {
      "sys": { "id": "83" },
      "fields": {
        "embeded": "<iframe src=\"https://www.facebook.com/plugins/post.php?href=https%3A%2F%2Fwww.facebook.com%2Frosaryplanthouse%2Fposts%2F297584888656542&show_text=true&width=500\" width=\"500\" height=\"575\" style=\"border:none;overflow:hidden\" scrolling=\"no\" frameborder=\"0\" allowfullscreen=\"true\" allow=\"autoplay; clipboard-write; encrypted-media; picture-in-picture; web-share\"></iframe>"
      }
    },
    {
      "sys": { "id": "84" },
      "fields": {
        "embeded": "<iframe src=\"https://www.facebook.com/plugins/post.php?href=https%3A%2F%2Fwww.facebook.com%2Frosaryplanthouse%2Fposts%2F334974464917584&show_text=true&width=500\" width=\"500\" height=\"668\" style=\"border:none;overflow:hidden\" scrolling=\"no\" frameborder=\"0\" allowfullscreen=\"true\" allow=\"autoplay; clipboard-write; encrypted-media; picture-in-picture; web-share\"></iframe>"
      }
    },
    {
      "sys": { "id": "85" },
      "fields": {
        "embeded": "<iframe src=\"https://www.facebook.com/plugins/post.php?href=https%3A%2F%2Fwww.facebook.com%2Frosaryplanthouse%2Fposts%2F334997224915308&show_text=true&width=500\" width=\"500\" height=\"535\" style=\"border:none;overflow:hidden\" scrolling=\"no\" frameborder=\"0\" allowfullscreen=\"true\" allow=\"autoplay; clipboard-write; encrypted-media; picture-in-picture; web-share\"></iframe>"
      }
    },
    {
      "sys": { "id": "86" },
      "fields": {
        "embeded": "<iframe src=\"https://www.facebook.com/plugins/post.php?href=https%3A%2F%2Fwww.facebook.com%2Frosaryplanthouse%2Fposts%2F337781761303521&show_text=true&width=500\" width=\"500\" height=\"640\" style=\"border:none;overflow:hidden\" scrolling=\"no\" frameborder=\"0\" allowfullscreen=\"true\" allow=\"autoplay; clipboard-write; encrypted-media; picture-in-picture; web-share\"></iframe>"
      }
    },
    {
      "sys": { "id": "87" },
      "fields": {
        "embeded": "<iframe src=\"https://www.facebook.com/plugins/post.php?href=https%3A%2F%2Fwww.facebook.com%2Frosaryplanthouse%2Fposts%2F339932414421789&show_text=true&width=500\" width=\"500\" height=\"608\" style=\"border:none;overflow:hidden\" scrolling=\"no\" frameborder=\"0\" allowfullscreen=\"true\" allow=\"autoplay; clipboard-write; encrypted-media; picture-in-picture; web-share\"></iframe>"
      }
    },
    {
      "sys": { "id": "88" },
      "fields": {
        "embeded": "<iframe src=\"https://www.facebook.com/plugins/post.php?href=https%3A%2F%2Fwww.facebook.com%2Frosaryplanthouse%2Fposts%2F340030911078606&show_text=true&width=500\" width=\"500\" height=\"645\" style=\"border:none;overflow:hidden\" scrolling=\"no\" frameborder=\"0\" allowfullscreen=\"true\" allow=\"autoplay; clipboard-write; encrypted-media; picture-in-picture; web-share\"></iframe>"
      }
    },
    {
      "sys": { "id": "89" },
      "fields": {
        "embeded": "<iframe src=\"https://www.facebook.com/plugins/post.php?href=https%3A%2F%2Fwww.facebook.com%2Frosaryplanthouse%2Fposts%2F340047614410269&show_text=true&width=500\" width=\"500\" height=\"466\" style=\"border:none;overflow:hidden\" scrolling=\"no\" frameborder=\"0\" allowfullscreen=\"true\" allow=\"autoplay; clipboard-write; encrypted-media; picture-in-picture; web-share\"></iframe>"
      }
    },
    {
      "sys": { "id": "90" },
      "fields": {
        "embeded": "<iframe src=\"https://www.facebook.com/plugins/post.php?href=https%3A%2F%2Fwww.facebook.com%2Frosaryplanthouse%2Fposts%2F340082417740122&show_text=true&width=500\" width=\"500\" height=\"452\" style=\"border:none;overflow:hidden\" scrolling=\"no\" frameborder=\"0\" allowfullscreen=\"true\" allow=\"autoplay; clipboard-write; encrypted-media; picture-in-picture; web-share\"></iframe>"
      }
    },
    {
      "sys": { "id": "91" },
      "fields": {
        "embeded": "<iframe src=\"https://www.facebook.com/plugins/post.php?href=https%3A%2F%2Fwww.facebook.com%2Frosaryplanthouse%2Fposts%2F342795907468773&show_text=true&width=500\" width=\"500\" height=\"665\" style=\"border:none;overflow:hidden\" scrolling=\"no\" frameborder=\"0\" allowfullscreen=\"true\" allow=\"autoplay; clipboard-write; encrypted-media; picture-in-picture; web-share\"></iframe>"
      }
    },
    {
      "sys": { "id": "92" },
      "fields": {
        "embeded": "<iframe src=\"https://www.facebook.com/plugins/post.php?href=https%3A%2F%2Fwww.facebook.com%2Frosaryplanthouse%2Fposts%2F345145827233781&show_text=true&width=500\" width=\"500\" height=\"742\" style=\"border:none;overflow:hidden\" scrolling=\"no\" frameborder=\"0\" allowfullscreen=\"true\" allow=\"autoplay; clipboard-write; encrypted-media; picture-in-picture; web-share\"></iframe>"
      }
    },
    {
      "sys": { "id": "93" },
      "fields": {
        "embeded": "<iframe src=\"https://www.facebook.com/plugins/post.php?href=https%3A%2F%2Fwww.facebook.com%2Frosaryplanthouse%2Fposts%2F350704633344567&show_text=true&width=500\" width=\"500\" height=\"524\" style=\"border:none;overflow:hidden\" scrolling=\"no\" frameborder=\"0\" allowfullscreen=\"true\" allow=\"autoplay; clipboard-write; encrypted-media; picture-in-picture; web-share\"></iframe>"
      }
    },
    {
      "sys": { "id": "94" },
      "fields": {
        "embeded": "<iframe src=\"https://www.facebook.com/plugins/post.php?href=https%3A%2F%2Fwww.facebook.com%2Frosaryplanthouse%2Fposts%2F368351341579896&show_text=true&width=500\" width=\"500\" height=\"207\" style=\"border:none;overflow:hidden\" scrolling=\"no\" frameborder=\"0\" allowfullscreen=\"true\" allow=\"autoplay; clipboard-write; encrypted-media; picture-in-picture; web-share\"></iframe>"
      }
    },
    {
      "sys": { "id": "95" },
      "fields": {
        "embeded": "<iframe src=\"https://www.facebook.com/plugins/post.php?href=https%3A%2F%2Fwww.facebook.com%2Frosaryplanthouse%2Fposts%2F369610361453994&show_text=true&width=500\" width=\"500\" height=\"665\" style=\"border:none;overflow:hidden\" scrolling=\"no\" frameborder=\"0\" allowfullscreen=\"true\" allow=\"autoplay; clipboard-write; encrypted-media; picture-in-picture; web-share\"></iframe>"
      }
    },
    {
      "sys": { "id": "96" },
      "fields": {
        "embeded": "<iframe src=\"https://www.facebook.com/plugins/post.php?href=https%3A%2F%2Fwww.facebook.com%2Frosaryplanthouse%2Fposts%2F377747630640267&show_text=true&width=500\" width=\"500\" height=\"537\" style=\"border:none;overflow:hidden\" scrolling=\"no\" frameborder=\"0\" allowfullscreen=\"true\" allow=\"autoplay; clipboard-write; encrypted-media; picture-in-picture; web-share\"></iframe>"
      }
    },
    {
      "sys": { "id": "97" },
      "fields": {
        "embeded": "<iframe src=\"https://www.facebook.com/plugins/post.php?href=https%3A%2F%2Fwww.facebook.com%2Frosaryplanthouse%2Fposts%2F378869490528081&show_text=true&width=500\" width=\"500\" height=\"628\" style=\"border:none;overflow:hidden\" scrolling=\"no\" frameborder=\"0\" allowfullscreen=\"true\" allow=\"autoplay; clipboard-write; encrypted-media; picture-in-picture; web-share\"></iframe>"
      }
    },
    {
      "sys": { "id": "98" },
      "fields": {
        "embeded": "<iframe src=\"https://www.facebook.com/plugins/post.php?href=https%3A%2F%2Fwww.facebook.com%2Frosaryplanthouse%2Fposts%2F435457144869315&show_text=true&width=500\" width=\"500\" height=\"186\" style=\"border:none;overflow:hidden\" scrolling=\"no\" frameborder=\"0\" allowfullscreen=\"true\" allow=\"autoplay; clipboard-write; encrypted-media; picture-in-picture; web-share\"></iframe>"
      }
    },
    {
      "sys": { "id": "99" },
      "fields": {
        "embeded": "<iframe src=\"https://www.facebook.com/plugins/post.php?href=https%3A%2F%2Fwww.facebook.com%2Frosaryplanthouse%2Fposts%2F438635567884806&show_text=true&width=500\" width=\"500\" height=\"665\" style=\"border:none;overflow:hidden\" scrolling=\"no\" frameborder=\"0\" allowfullscreen=\"true\" allow=\"autoplay; clipboard-write; encrypted-media; picture-in-picture; web-share\"></iframe>"
      }
    },
    {
      "sys": { "id": "100" },
      "fields": {
        "embeded": "<iframe src=\"https://www.facebook.com/plugins/post.php?href=https%3A%2F%2Fwww.facebook.com%2Frosaryplanthouse%2Fposts%2F439414257806937&show_text=true&width=500\" width=\"500\" height=\"582\" style=\"border:none;overflow:hidden\" scrolling=\"no\" frameborder=\"0\" allowfullscreen=\"true\" allow=\"autoplay; clipboard-write; encrypted-media; picture-in-picture; web-share\"></iframe>"
      }
    },
    {
      "sys": { "id": "101" },
      "fields": {
        "embeded": "<iframe src=\"https://www.facebook.com/plugins/post.php?href=https%3A%2F%2Fwww.facebook.com%2Frosaryplanthouse%2Fposts%2F444033040678392&show_text=true&width=500\" width=\"500\" height=\"744\" style=\"border:none;overflow:hidden\" scrolling=\"no\" frameborder=\"0\" allowfullscreen=\"true\" allow=\"autoplay; clipboard-write; encrypted-media; picture-in-picture; web-share\"></iframe>"
      }
    },
    {
      "sys": { "id": "102" },
      "fields": {
        "embeded": "<iframe src=\"https://www.facebook.com/plugins/post.php?href=https%3A%2F%2Fwww.facebook.com%2Frosaryplanthouse%2Fposts%2F444247497323613&show_text=true&width=500\" width=\"500\" height=\"589\" style=\"border:none;overflow:hidden\" scrolling=\"no\" frameborder=\"0\" allowfullscreen=\"true\" allow=\"autoplay; clipboard-write; encrypted-media; picture-in-picture; web-share\"></iframe>"
      }
    },
    {
      "sys": { "id": "103" },
      "fields": {
        "embeded": "<iframe src=\"https://www.facebook.com/plugins/post.php?href=https%3A%2F%2Fwww.facebook.com%2Frosaryplanthouse%2Fposts%2F444249313990098&show_text=true&width=500\" width=\"500\" height=\"186\" style=\"border:none;overflow:hidden\" scrolling=\"no\" frameborder=\"0\" allowfullscreen=\"true\" allow=\"autoplay; clipboard-write; encrypted-media; picture-in-picture; web-share\"></iframe>"
      }
    },
    {
      "sys": { "id": "104" },
      "fields": {
        "embeded": "<iframe src=\"https://www.facebook.com/plugins/post.php?href=https%3A%2F%2Fwww.facebook.com%2Frosaryplanthouse%2Fposts%2F448034240278272&show_text=true&width=500\" width=\"500\" height=\"781\" style=\"border:none;overflow:hidden\" scrolling=\"no\" frameborder=\"0\" allowfullscreen=\"true\" allow=\"autoplay; clipboard-write; encrypted-media; picture-in-picture; web-share\"></iframe>"
      }
    },
    {
      "sys": { "id": "105" },
      "fields": {
        "embeded": "<iframe src=\"https://www.facebook.com/plugins/post.php?href=https%3A%2F%2Fwww.facebook.com%2Frosaryplanthouse%2Fposts%2F452302749851421&show_text=true&width=500\" width=\"500\" height=\"475\" style=\"border:none;overflow:hidden\" scrolling=\"no\" frameborder=\"0\" allowfullscreen=\"true\" allow=\"autoplay; clipboard-write; encrypted-media; picture-in-picture; web-share\"></iframe>"
      }
    },
    {
      "sys": { "id": "106" },
      "fields": {
        "embeded": "<iframe src=\"https://www.facebook.com/plugins/post.php?href=https%3A%2F%2Fwww.facebook.com%2Frosaryplanthouse%2Fposts%2F454740542940975&show_text=true&width=500\" width=\"500\" height=\"645\" style=\"border:none;overflow:hidden\" scrolling=\"no\" frameborder=\"0\" allowfullscreen=\"true\" allow=\"autoplay; clipboard-write; encrypted-media; picture-in-picture; web-share\"></iframe>"
      }
    },
    {
      "sys": { "id": "107" },
      "fields": {
        "embeded": "<iframe src=\"https://www.facebook.com/plugins/post.php?href=https%3A%2F%2Fwww.facebook.com%2Frosaryplanthouse%2Fposts%2F483169103431452&show_text=true&width=500\" width=\"500\" height=\"466\" style=\"border:none;overflow:hidden\" scrolling=\"no\" frameborder=\"0\" allowfullscreen=\"true\" allow=\"autoplay; clipboard-write; encrypted-media; picture-in-picture; web-share\"></iframe>"
      }
    },
    {
      "sys": { "id": "108" },
      "fields": {
        "embeded": "<iframe src=\"https://www.facebook.com/plugins/post.php?href=https%3A%2F%2Fwww.facebook.com%2Frosaryplanthouse%2Fposts%2F484446019970427&show_text=true&width=500\" width=\"500\" height=\"819\" style=\"border:none;overflow:hidden\" scrolling=\"no\" frameborder=\"0\" allowfullscreen=\"true\" allow=\"autoplay; clipboard-write; encrypted-media; picture-in-picture; web-share\"></iframe>"
      }
    },
    {
      "sys": { "id": "109" },
      "fields": {
        "embeded": "<iframe src=\"https://www.facebook.com/plugins/post.php?href=https%3A%2F%2Fwww.facebook.com%2Frosaryplanthouse%2Fposts%2F485745579840471&show_text=true&width=500\" width=\"500\" height=\"645\" style=\"border:none;overflow:hidden\" scrolling=\"no\" frameborder=\"0\" allowfullscreen=\"true\" allow=\"autoplay; clipboard-write; encrypted-media; picture-in-picture; web-share\"></iframe>"
      }
    },
    {
      "sys": { "id": "110" },
      "fields": {
        "embeded": "<iframe src=\"https://www.facebook.com/plugins/post.php?href=https%3A%2F%2Fwww.facebook.com%2Frosaryplanthouse%2Fposts%2F488163599598669&show_text=true&width=500\" width=\"500\" height=\"665\" style=\"border:none;overflow:hidden\" scrolling=\"no\" frameborder=\"0\" allowfullscreen=\"true\" allow=\"autoplay; clipboard-write; encrypted-media; picture-in-picture; web-share\"></iframe>"
      }
    },
    {
      "sys": { "id": "111" },
      "fields": {
        "embeded": "<iframe src=\"https://www.facebook.com/plugins/post.php?href=https%3A%2F%2Fwww.facebook.com%2Frosaryplanthouse%2Fposts%2F490578696023826&show_text=true&width=500\" width=\"500\" height=\"629\" style=\"border:none;overflow:hidden\" scrolling=\"no\" frameborder=\"0\" allowfullscreen=\"true\" allow=\"autoplay; clipboard-write; encrypted-media; picture-in-picture; web-share\"></iframe>"
      }
    },
    {
      "sys": { "id": "112" },
      "fields": {
        "embeded": "<iframe src=\"https://www.facebook.com/plugins/post.php?href=https%3A%2F%2Fwww.facebook.com%2Frosaryplanthouse%2Fposts%2F510734477341581&show_text=true&width=500\" width=\"500\" height=\"536\" style=\"border:none;overflow:hidden\" scrolling=\"no\" frameborder=\"0\" allowfullscreen=\"true\" allow=\"autoplay; clipboard-write; encrypted-media; picture-in-picture; web-share\"></iframe>"
      }
    },
    {
      "sys": { "id": "113" },
      "fields": {
        "embeded": "<iframe src=\"https://www.facebook.com/plugins/post.php?href=https%3A%2F%2Fwww.facebook.com%2Frosaryplanthouse%2Fposts%2F513140950434267&show_text=true&width=500\" width=\"500\" height=\"169\" style=\"border:none;overflow:hidden\" scrolling=\"no\" frameborder=\"0\" allowfullscreen=\"true\" allow=\"autoplay; clipboard-write; encrypted-media; picture-in-picture; web-share\"></iframe>"
      }
    },
    {
      "sys": { "id": "114" },
      "fields": {
        "embeded": "<iframe src=\"https://www.facebook.com/plugins/post.php?href=https%3A%2F%2Fwww.facebook.com%2Frosaryplanthouse%2Fposts%2F528850278863334&show_text=true&width=500\" width=\"500\" height=\"582\" style=\"border:none;overflow:hidden\" scrolling=\"no\" frameborder=\"0\" allowfullscreen=\"true\" allow=\"autoplay; clipboard-write; encrypted-media; picture-in-picture; web-share\"></iframe>"
      }
    },
    {
      "sys": { "id": "115" },
      "fields": {
        "embeded": "<iframe src=\"https://www.facebook.com/plugins/post.php?href=https%3A%2F%2Fwww.facebook.com%2Frosaryplanthouse%2Fposts%2F533335561748139&show_text=true&width=500\" width=\"500\" height=\"645\" style=\"border:none;overflow:hidden\" scrolling=\"no\" frameborder=\"0\" allowfullscreen=\"true\" allow=\"autoplay; clipboard-write; encrypted-media; picture-in-picture; web-share\"></iframe>"
      }
    },
    {
      "sys": { "id": "116" },
      "fields": {
        "embeded": "<iframe src=\"https://www.facebook.com/plugins/post.php?href=https%3A%2F%2Fwww.facebook.com%2Frosaryplanthouse%2Fposts%2F533576441724051&show_text=true&width=500\" width=\"500\" height=\"205\" style=\"border:none;overflow:hidden\" scrolling=\"no\" frameborder=\"0\" allowfullscreen=\"true\" allow=\"autoplay; clipboard-write; encrypted-media; picture-in-picture; web-share\"></iframe>"
      }
    },
    {
      "sys": { "id": "117" },
      "fields": {
        "embeded": "<iframe src=\"https://www.facebook.com/plugins/post.php?href=https%3A%2F%2Fwww.facebook.com%2Frosaryplanthouse%2Fposts%2F533877381693957&show_text=true&width=500\" width=\"500\" height=\"169\" style=\"border:none;overflow:hidden\" scrolling=\"no\" frameborder=\"0\" allowfullscreen=\"true\" allow=\"autoplay; clipboard-write; encrypted-media; picture-in-picture; web-share\"></iframe>"
      }
    },
    { "sys": { "id": "" }, "fields": { "embeded": "" } }
  ]
}
